mxwpy/__init__.py
mxwpy/linalg.py
mxwpy/npde.py
mxwpy/spectral.py
mxwpy/tools.py
mxwpy-0.2.3.dist-info/LICENSE
mxwpy-0.2.3.dist-info/METADATA
mxwpy-0.2.3.dist-info/WHEEL
mxwpy-0.2.3.dist-info/top_level.txt
mxwpy-0.2.3.dist-info/RECORD
