Metadata-Version: 2.1
Name: mxwpy
Version: 0.2.3
Summary: efficient numerical schemes
Home-page: https://github.com/mxweng/mxwpy
Author: MXWeng
Author-email: 2431141461@qq.com
Classifier: Development Status :: 3 - Alpha
Classifier: License :: OSI Approved :: MIT License
Classifier: Operating System :: OS Independent
Classifier: Programming Language :: Python :: 3
Classifier: Programming Language :: Python :: 3.8
Classifier: Programming Language :: Python :: 3.9
Classifier: Programming Language :: Python :: 3.10
Classifier: Programming Language :: Python :: 3.11
Classifier: Programming Language :: Python :: 3.12
Classifier: Intended Audience :: Science/Research
Classifier: Topic :: Scientific/Engineering :: Mathematics
Requires-Python: >=3.6
License-File: LICENSE
Requires-Dist: GPUtil
Requires-Dist: IPython
Requires-Dist: numpy
Requires-Dist: pandas
Requires-Dist: psutil
Requires-Dist: scipy
Requires-Dist: sympy
